edxia/__init__.py
edxia/analysis/__init__.py
edxia/analysis/correlation.py
edxia/analysis/helpers.py
edxia/analysis/point_counting.py
edxia/composite/__init__.py
edxia/composite/channels.py
edxia/composite/color_analysis.py
edxia/composite/composite.py
edxia/composite/segmentation.py
edxia/core/__init__.py
edxia/core/experiment.py
edxia/core/map.py
edxia/filters/__init__.py
edxia/filters/base_filter.py
edxia/filters/denoise.py
edxia/filters/scalers.py
edxia/glue/__init__.py
edxia/glue/arithmetic_data.py
edxia/glue/create_data.py
edxia/glue/link_data.py
edxia/glue/map_coordinates.py
edxia/glue/phase_data.py
edxia/glue/pretty_plot.py
edxia/glue/qt/__init__.py
edxia/glue/qt/bse_editor.py
edxia/glue/qt/bse_editor.ui
edxia/glue/qt/exporter.py
edxia/glue/qt/linker.py
edxia/glue/qt/loader.py
edxia/glue/qt/loader.ui
edxia/glue/qt/phase_add.ui
edxia/glue/qt/phases.py
edxia/glue/qt/phases.ui
edxia/glue/qt/points_loader.py
edxia/glue/qt/points_loader.ui
edxia/glue/qt/subset_quantifier.py
edxia/glue/qt/quantifier/composition.ui
edxia/glue/qt/quantifier/main_quantifier.ui
edxia/glue/qt/quantifier/point_fractions.ui
edxia/glue/qt/quantifier/s2_correlation.ui
edxia/glue/qt/quantifier/surface_fractions.ui
edxia/io/__init__.py
edxia/io/hdf5.py
edxia/io/raw_io.py
edxia/io/loader/__init__.py
edxia/io/loader/base_loader.py
edxia/io/loader/default_loader.py
edxia/io/loader/pickle_loader.py
edxia/io/loader/stack_loader.py
edxia/point_analysis/__init__.py
edxia/point_analysis/points.py
edxia/utils/__init__.py
edxia/utils/chemistry.py
edxia/utils/coordinates.py
edxia/utils/path.py
edxia/utils/qt.py
edxia-0.1.15.dist-info/LICENSE.txt
edxia-0.1.15.dist-info/METADATA
edxia-0.1.15.dist-info/WHEEL
edxia-0.1.15.dist-info/entry_points.txt
edxia-0.1.15.dist-info/top_level.txt
edxia-0.1.15.dist-info/RECORD
