Metadata-Version: 2.1
Name: edxia
Version: 0.1.15
Summary: SEM-BSE-EDS image analysis
Home-page: https://bitbucket.org/specmicp/edxia/
Author: Fabien Georget
Author-email: georget@ibac.rwth-aachen.de
License: BSD
Project-URL: Funding, https://lmc.epfl.ch/
Keywords: SEM EDS BSE visualization
Classifier: Development Status :: 3 - Alpha
Classifier: Intended Audience :: Science/Research
Classifier: Topic :: Scientific/Engineering :: Chemistry
Classifier: Topic :: Scientific/Engineering :: Visualization
Classifier: License :: OSI Approved :: BSD License
Classifier: Programming Language :: Python :: 3
Classifier: Programming Language :: Python :: 3.8
Classifier: Programming Language :: Python :: 3.9
Classifier: Programming Language :: Python :: 3.10
Classifier: Programming Language :: Python :: 3.11
Classifier: Programming Language :: Python :: 3.12
Classifier: Programming Language :: Python :: 3.13
Requires-Python: >=3.5, <4
License-File: LICENSE.txt
Requires-Dist: glueviz >=0.15
Requires-Dist: glue-core
Requires-Dist: glue-qt
Requires-Dist: pandas
Requires-Dist: py-expression-eval
Requires-Dist: scikit-image
Requires-Dist: scikit-learn
Requires-Dist: numba
Requires-Dist: h5py
Provides-Extra: jointbilateral
Requires-Dist: opencv-contrib-python ; extra == 'jointbilateral'
